Workbook

Sheet Summary
A1: Value at Risk - Portfolio of JPM, MS & BAC (1-day, $1,000,000, equal weights by default)
A2: Data: Yahoo Finance daily adjusted close, 2024-10-31 to 2026-10-30 (500 daily returns). Change weights / value / holding period on each method sheet (yellow cells).
A4: Confidence level | B4: Variance-Covariance VaR | C4: Historical VaR | D4: Monte Carlo VaR
A5: 0.9 | B5: =VarCov_Method!$D$39 -> 19044.603 | C5: =Historical_Method!$E$16 -> 17262.92 | D5: =MonteCarlo_Method!$E$29 -> 19132.083
A6: 0.95 | B6: =VarCov_Method!$D$40 -> 24709.757 | C6: =Historical_Method!$E$17 -> 23940.841 | D6: =MonteCarlo_Method!$E$30 -> 25023.054
A7: 0.99 | B7: =VarCov_Method!$D$41 -> 35336.643 | C7: =Historical_Method!$E$18 -> 42713.764 | D7: =MonteCarlo_Method!$E$31 -> 35552.568
A10: How to read this workbook
A12: Sheets
A13: Data - Step 1 & 2 for every method: Yahoo Finance prices and daily returns.
A14: Backtesting - rolling 250-day out-of-sample VaR for all 3 methods, exceptions, Basel Traffic Light and Kupiec POF test.
A15: VarCov_Method - parametric VaR using mean, std dev, covariance matrix and Z-scores.
A16: Historical_Method - VaR from the actual distribution of past portfolio returns.
A17: MonteCarlo_Method - VaR from 10,000 correlated simulated scenarios (press F9 to re-simulate).
A18: VaR definition: the loss that will not be exceeded with X% confidence over the holding period (e.g. 95% 1-day VaR of $20k = on 95 out of 100 days the loss should be below $20k).

Sheet Data
A1: STEP 1 & 2: Collect price data and calculate daily returns
A2: Source: Yahoo Finance (yfinance), daily adjusted close (dividends/splits adjusted). 2024-10-31 to 2026-10-30 | 501 prices -> 500 daily returns
A3: Daily simple return formula: R_t = P_t / P_(t-1) - 1 (log return shown for reference: LN(P_t/P_(t-1)))
A5: Date | B5: JPM Adj Close | C5: MS Adj Close | D5: BAC Adj Close | F5: JPM Return | G5: MS Return | H5: BAC Return | J5: JPM Log Return | K5: MS Log Return | L5: BAC Log Return
A6: 45596 | B6: 213.21313 | C6: 110.57666 | D6: 40.005711
A7: 45597 | B7: 214.19315 | C7: 111.14738 | D7: 39.948311 | F7: =B7/B6-1 -> 0.0045963912 | G7: =C7/C6-1 -> 0.0051613468 | H7: =D7/D6-1 -> -0.0014347889 | J7: =LN(B7/B6) -> 0.0045858601 | K7: =LN(C7/C6) -> 0.0051480727 | L7: =LN(D7/D6) -> -0.0014358192
A8: 45600 | B8: 211.15709 | C8: 110.47202 | D8: 39.536972 | F8: =B8/B7-1 -> -0.014174387 | G8: =C8/C7-1 -> -0.0060763397 | H8: =D8/D7-1 -> -0.010296776 | J8: =LN(B8/B7) -> -0.014275803 | K8: =LN(C8/C7) -> -0.0060948757 | L8: =LN(D8/D7) -> -0.010350154
A9: 45601 | B9: 212.80003 | C9: 112.06052 | D9: 40.063099 | F9: =B9/B8-1 -> 0.0077806733 | G9: =C9/C8-1 -> 0.014379216 | H9: =D9/D8-1 -> 0.013307212 | J9: =LN(B9/B8) -> 0.00775056 | K9: =LN(C9/C8) -> 0.014276816 | L9: =LN(D9/D8) -> 0.013219449
A10: 45602 | B10: 237.36678 | C10: 125.0729 | D10: 43.439957 | F10: =B10/B9-1 -> 0.1154452 | G10: =C10/C9-1 -> 0.11611924 | H10: =D10/D9-1 -> 0.084288481 | J10: =LN(B10/B9) -> 0.10925361 | K10: =LN(C10/C9) -> 0.10985771 | L10: =LN(D10/D9) -> 0.080923994
A11: 45603 | B11: 227.10583 | C11: 122.17175 | D11: 42.827724 | F11: =B11/B10-1 -> -0.043228209 | G11: =C11/C10-1 -> -0.023195701 | H11: =D11/D10-1 -> -0.014093757 | J11: =LN(B11/B10) -> -0.044190379 | K11: =LN(C11/C10) -> -0.023468955 | L11: =LN(D11/D10) -> -0.014194017
A12: 45604 | B12: 227.68225 | C12: 123.20855 | D12: 43.172112 | F12: =B12/B11-1 -> 0.0025380943 | G12: =C12/C11-1 -> 0.0084864483 | H12: =D12/D11-1 -> 0.0080412177 | J12: =LN(B12/B11) -> 0.0025348787 | K12: =LN(C12/C11) -> 0.0084506408 | L12: =LN(D12/D11) -> 0.0080090594
A13: 45607 | B13: 229.90164 | C13: 127.00382 | D13: 44.080898 | F13: =B13/B12-1 -> 0.0097477553 | G13: =C13/C12-1 -> 0.030803648 | H13: =D13/D12-1 -> 0.02105032 | J13: =LN(B13/B12) -> 0.0097005524 | K13: =LN(C13/C12) -> 0.030338739 | L13: =LN(D13/D12) -> 0.020831823
A14: 45608 | B14: 230.16106 | C14: 125.8529 | D14: 43.870441 | F14: =B14/B13-1 -> 0.0011283724 | G14: =C14/C13-1 -> -0.0090621263 | H14: =D14/D13-1 -> -0.0047743321 | J14: =LN(B14/B13) -> 0.0011277363 | K14: =LN(C14/C13) -> -0.0091034372 | L14: =LN(D14/D13) -> -0.0047857656
A15: 45609 | B15: 231.69827 | C15: 126.2809 | D15: 43.880001 | F15: =B15/B14-1 -> 0.0066788718 | G15: =C15/C14-1 -> 0.0034008069 | H15: =D15/D14-1 -> 0.00021790598 | J15: =LN(B15/B14) -> 0.0066566669 | K15: =LN(C15/C14) -> 0.0033950372 | L15: =LN(D15/D14) -> 0.00021788224
A16: 45610 | B16: 232.38042 | C16: 125.967 | D16: 43.908703 | F16: =B16/B15-1 -> 0.0029441055 | G16: =C16/C15-1 -> -0.002485698 | H16: =D16/D15-1 -> 0.00065409712 | J16: =LN(B16/B15) -> 0.0029397801 | K16: =LN(C16/C15) -> -0.0024887925 | L16: =LN(D16/D15) -> 0.00065388329
A17: 45611 | B17: 235.68546 | C17: 127.51746 | D17: 44.721828 | F17: =B17/B16-1 -> 0.014222534 | G17: =C17/C16-1 -> 0.012308468 | H17: =D17/D16-1 -> 0.018518552 | J17: =LN(B17/B16) -> 0.014122343 | K17: =LN(C17/C16) -> 0.012233335 | L17: =LN(D17/D16) -> 0.018349172
A18: 45614 | B18: 235.41644 | C18: 127.25115 | D18: 44.693127 | F18: =B18/B17-1 -> -0.0011414046 | G18: =C18/C17-1 -> -0.0020884327 | H18: =D18/D17-1 -> -0.00064178463 | J18: =LN(B18/B17) -> -0.0011420564 | K18: =LN(C18/C17) -> -0.0020906166 | L18: =LN(D18/D17) -> -0.00064199066
... A506: 46325 | B506: 337.04001 | C506: 184.3 | D506: 50.009998 | F506: =B506/B505-1 -> -0.019034805 | G506: =C506/C505-1 -> -0.024093211 | H506: =D506/D505-1 -> -0.022096228 | J506: =LN(B506/B505) -> -0.019218299 | K506: =LN(C506/C505) -> -0.0243882 | L506: =LN(D506/D505) -> -0.022344006

Sheet VarCov_Method
A1: VaR - Variance-Covariance (Parametric / Delta-Normal) Method | K1: Method notes
A3: INPUTS (yellow cells are editable) | K3: Steps performed
A4: Portfolio value ($) | B4: 1000000 | K4: 1. Collect data: downloaded daily adjusted closing prices for JPM, MS and BAC from Yahoo Finance (Data sheet).
A5: Holding period (days) | B5: 1 | K5: 2. Calculate returns: daily simple returns R_t = P_t / P_(t-1) - 1 for each stock.
A6: Stock | B6: Weight | C6: Position ($) | K6: 3. Calculate mean (AVERAGE) and standard deviation (STDEV.S) of each stock's daily returns.
A7: JPM (JPMorgan Chase) | B7: 0.33333333 | C7: =$B$4*B7 -> 333333.33 | K7: 4. Build the variance-covariance matrix (COVARIANCE.S) - captures how the stocks move together (correlation shown alongside).
A8: MS (Morgan Stanley) | B8: 0.33333333 | C8: =$B$4*B8 -> 333333.33 | K8: 5. Combine with portfolio weights: portfolio variance = w' x COV x w; portfolio sigma = SQRT(variance); portfolio mean = SUMPRODUCT(w, mu).
A9: BAC (Bank of America) | B9: 0.33333333 | C9: =$B$4*B9 -> 333333.33 | K9: 6. Get Z-score for 90% / 95% / 99% with NORM.S.INV(CI) (1.2816 / 1.6449 / 2.3263).
A10: Total | B10: =SUM(B7:B9) -> 1 | C10: =SUM(C7:C9) -> 1000000 | K10: 7. VaR = (Z x sigma_p - mu_p) x Portfolio Value x SQRT(holding period). Zero-mean version (Z x sigma x V) also shown.
K11: 8. Diversification benefit = undiversified VaR (sum of stand-alone risks) - portfolio VaR.
A12: STEP 1-2: Data collected & daily returns calculated on 'Data' sheet (Adj Close -> R_t = P_t/P_t-1 - 1)
K13: Assumptions
A14: STEP 3: Mean & standard deviation of daily returns (each stock) | K14: Portfolio (and stock) returns are normally distributed.
A15: Statistic | B15: JPM | C15: MS | D15: BAC | K15: Mean, volatility and correlations are constant (stationary) over the look-back window and the holding period.
A16: Mean daily return =AVERAGE() | B16: =AVERAGE(Data!$F$7:$F$506) -> 0.0010359072 | C16: =AVERAGE(Data!$G$7:$G$506) -> 0.0012091414 | D16: =AVERAGE(Data!$H$7:$H$506) -> 0.00057279405 | K16: Positions are linear in risk factors (no options/convexity) and the portfolio is held constant over the horizon.
A17: Std dev daily =STDEV.S() | B17: =_xlfn.STDEV.S(Data!$F$7:$F$506) -> 0.015510582 | C17: =_xlfn.STDEV.S(Data!$G$7:$G$506) -> 0.019376095 | D17: =_xlfn.STDEV.S(Data!$H$7:$H$506) -> 0.015833217 | K17: Returns are i.i.d., so multi-day VaR scales with SQRT(T) (square-root-of-time rule).
A18: Variance daily =VAR.S() | B18: =_xlfn.VAR.S(Data!$F$7:$F$506) -> 0.00024057815 | C18: =_xlfn.VAR.S(Data!$G$7:$G$506) -> 0.00037543307 | D18: =_xlfn.VAR.S(Data!$H$7:$H$506) -> 0.00025069075
A19: Annualised vol (x SQRT(252)) | B19: =B17*SQRT(252) -> 0.24622286 | C19: =C17*SQRT(252) -> 0.30758598 | D19: =D17*SQRT(252) -> 0.25134452 | K19: Pros
K20: Simple, fast and transparent - only needs means, volatilities and correlations.
A21: STEP 4: Covariance matrix =COVARIANCE.S(Ri, Rj) and correlation matrix =CORREL(Ri, Rj) | K21: Easy to scale to other confidence levels and horizons; easy to decompose risk by position (component/marginal VaR).
A22: Covariance | B22: JPM | C22: MS | D22: BAC | F22: Correlation | G22: JPM | H22: MS | I22: BAC | K22: Explicitly captures diversification through the covariance matrix.
A23: JPM | B23: =_xlfn.COVARIANCE.S(Data!$F$7:$F$506,Data!$F$7:$F$506) -> 0.00024057815 | C23: =_xlfn.COVARIANCE.S(Data!$F$7:$F$506,Data!$G$7:$G$506) -> 0.00023059516 | D23: =_xlfn.COVARIANCE.S(Data!$F$7:$F$506,Data!$H$7:$H$506) -> 0.00019348421 | F23: JPM | G23: =CORREL(Data!$F$7:$F$506,Data!$F$7:$F$506) -> 1 | H23: =CORREL(Data!$F$7:$F$506,Data!$G$7:$G$506) -> 0.76728344 | I23: =CORREL(Data!$F$7:$F$506,Data!$H$7:$H$506) -> 0.78785861
A24: MS | B24: =_xlfn.COVARIANCE.S(Data!$G$7:$G$506,Data!$F$7:$F$506) -> 0.00023059516 | C24: =_xlfn.COVARIANCE.S(Data!$G$7:$G$506,Data!$G$7:$G$506) -> 0.00037543307 | D24: =_xlfn.COVARIANCE.S(Data!$G$7:$G$506,Data!$H$7:$H$506) -> 0.00023677833 | F24: MS | G24: =CORREL(Data!$G$7:$G$506,Data!$F$7:$F$506) -> 0.76728344 | H24: =CORREL(Data!$G$7:$G$506,Data!$G$7:$G$506) -> 1 | I24: =CORREL(Data!$G$7:$G$506,Data!$H$7:$H$506) -> 0.77180312 | K24: Cons
A25: BAC | B25: =_xlfn.COVARIANCE.S(Data!$H$7:$H$506,Data!$F$7:$F$506) -> 0.00019348421 | C25: =_xlfn.COVARIANCE.S(Data!$H$7:$H$506,Data!$G$7:$G$506) -> 0.00023677833 | D25: =_xlfn.COVARIANCE.S(Data!$H$7:$H$506,Data!$H$7:$H$506) -> 0.00025069075 | F25: BAC | G25: =CORREL(Data!$H$7:$H$506,Data!$F$7:$F$506) -> 0.78785861 | H25: =CORREL(Data!$H$7:$H$506,Data!$G$7:$G$506) -> 0.77180312 | I25: =CORREL(Data!$H$7:$H$506,Data!$H$7:$H$506) -> 1 | K25: Normality assumption underestimates fat tails - VaR at 99% is often too low in a crisis.
K26: Poor for non-linear instruments (options) and skewed return distributions.
A27: STEP 5: Portfolio mean, variance and std dev sigma_p^2 = w' * COV * w | K27: Covariance estimates are unstable and backward-looking; correlations tend to rise in crashes.
A28: Item | B28: Value | K28: Like all VaR, says nothing about the size of losses beyond the VaR threshold.
A29: (COV * w) for JPM | B29: =$B$23*$B$7+$C$23*$B$8+$D$23*$B$9 -> 0.00022155251
A30: (COV * w) for MS | B30: =$B$24*$B$7+$C$24*$B$8+$D$24*$B$9 -> 0.00028093552
A31: (COV * w) for BAC | B31: =$B$25*$B$7+$C$25*$B$8+$D$25*$B$9 -> 0.00022698443
A32: Portfolio variance w'·COV·w | B32: =SUMPRODUCT($B$7:$B$9,B29:B31) -> 0.00024315748
A33: Portfolio std dev (daily) sigma_p | B33: =SQRT(B32) -> 0.015593508
A34: Portfolio mean (daily) mu_p = SUMPRODUCT(w, mu) | B34: =$B$7*$B$16+$B$8*$C$16+$B$9*$D$16 -> 0.00093928089
A35: Sum of weighted stand-alone std devs (no diversification) | B35: =$B$7*$B$17+$B$8*$C$17+$B$9*$D$17 -> 0.016906631
A37: STEP 6: Z-score for each confidence level =NORM.S.INV(CI) and VaR = (Z*sigma_p - mu_p) * V * SQRT(T)
A38: Confidence level | B38: Z-score | C38: VaR % (incl. mean) | D38: VaR $ (incl. mean) | E38: VaR $ (zero-mean, Z*sigma*V) | F38: Undiversified VaR $ | G38: Diversification benefit $
A39: 0.9 | B39: =_xlfn.NORM.S.INV(A39) -> 1.2815516 | C39: =(B39*$B$33-$B$34)*SQRT($B$5) -> 0.019044603 | D39: =C39*$B$4 -> 19044.603 | E39: =B39*$B$33*SQRT($B$5)*$B$4 -> 19983.884 | F39: =B39*$B$35*SQRT($B$5)*$B$4 -> 21666.72 | G39: =F39-E39 -> 1682.8355
A40: 0.95 | B40: =_xlfn.NORM.S.INV(A40) -> 1.6448536 | C40: =(B40*$B$33-$B$34)*SQRT($B$5) -> 0.024709757 | D40: =C40*$B$4 -> 24709.757 | E40: =B40*$B$33*SQRT($B$5)*$B$4 -> 25649.038 | F40: =B40*$B$35*SQRT($B$5)*$B$4 -> 27808.934 | G40: =F40-E40 -> 2159.896
A41: 0.99 | B41: =_xlfn.NORM.S.INV(A41) -> 2.3263479 | C41: =(B41*$B$33-$B$34)*SQRT($B$5) -> 0.035336643 | D41: =C41*$B$4 -> 35336.643 | E41: =B41*$B$33*SQRT($B$5)*$B$4 -> 36275.924 | F41: =B41*$B$35*SQRT($B$5)*$B$4 -> 39330.706 | G41: =F41-E41 -> 3054.7821
A43: STEP 7: Interpretation
A44: ="With 90% confidence, the portfolio should not lose more than "&TEXT(D39,"$#,##0")&" over "&$B$5&" day(s)." -> With 90% confidence, the portfolio should not lose more than $19,045 over 1 day(s).
A45: ="With 95% confidence, the portfolio should not lose more than "&TEXT(D40,"$#,##0")&" over "&$B$5&" day(s)." -> With 95% confidence, the portfolio should not lose more than $24,710 over 1 day(s).
A46: ="With 99% confidence, the portfolio should not lose more than "&TEXT(D41,"$#,##0")&" over "&$B$5&" day(s)." -> With 99% confidence, the portfolio should not lose more than $35,337 over 1 day(s).

Sheet Historical_Method
A1: VaR - Historical Simulation Method | K1: Method notes
A3: INPUTS (yellow cells are editable) | K3: Steps performed
A4: Portfolio value ($) | B4: 1000000 | K4: 1. Collect data: daily adjusted closing prices of JPM, MS, BAC from Yahoo Finance (Data sheet).
A5: Holding period (days) | B5: 1 | K5: 2. Calculate returns: daily simple returns for each stock.
A6: Stock | B6: Weight | C6: Position ($) | K6: 3. Calculate the portfolio's daily return for every historical day = SUMPRODUCT(weights, stock returns); P&L = return x portfolio value. (Each past day is a 'scenario' replayed on today's portfolio.)
A7: JPM (JPMorgan Chase) | B7: 0.33333333 | C7: =$B$4*B7 -> 333333.33 | K7: 4. Sort portfolio returns from worst to best (SMALL function, columns H-I).
A8: MS (Morgan Stanley) | B8: 0.33333333 | C8: =$B$4*B8 -> 333333.33 | K8: 5. VaR = the (1-CI) percentile of the sorted returns: PERCENTILE.INC(returns, 10% / 5% / 1%) x V. Rank method (k-th worst of N) shown as a check.
A9: BAC (Bank of America) | B9: 0.33333333 | C9: =$B$4*B9 -> 333333.33 | K9: 6. Expected Shortfall (CVaR) = average loss on days worse than VaR - shown as a bonus tail-risk measure.
A10: Total | B10: =SUM(B7:B9) -> 1 | C10: =SUM(C7:C9) -> 1000000
K11: Assumptions
A12: STEP 1-2: Data collected & daily returns calculated on 'Data' sheet | K12: The future will behave like the past - the historical window is representative of tomorrow's risk.
K13: Every historical day is equally likely (equal weighting of observations).
A14: STEP 4-5: Sort returns (worst -> best) & read the (1-CI) percentile: VaR = -PERCENTILE.INC(port. returns, 1-CI) x V | K14: No distributional assumption (non-parametric) - correlations are embedded in the actual data.
A15: Confidence level | B15: Tail prob (1-CI) | C15: Percentile return | D15: VaR % (1-day) | E15: VaR $ (x SQRT(T)) | F15: Rank-method: k = ROUNDUP((1-CI)*N) | G15: k-th worst return | H15: VaR $ (rank method) | I15: Expected Shortfall (CVaR) $ | K15: Multi-day VaR uses SQRT(T) scaling (assumes i.i.d. returns).
A16: 0.9 | B16: =1-A16 -> 0.1 | C16: =_xlfn.PERCENTILE.INC($E$25:$E$524,B16) -> -0.01726292 | D16: =-C16 -> 0.01726292 | E16: =D16*$B$4*SQRT($B$5) -> 17262.92 | F16: =ROUNDUP(B16*$B$20,0) -> 50 | G16: =SMALL($E$25:$E$524,F16) -> -0.01742674 | H16: =-G16*$B$4*SQRT($B$5) -> 17426.74 | I16: =-AVERAGEIF($E$25:$E$524,"<="&C16)*$B$4*SQRT($B$5) -> 28403.398
A17: 0.95 | B17: =1-A17 -> 0.05 | C17: =_xlfn.PERCENTILE.INC($E$25:$E$524,B17) -> -0.023940841 | D17: =-C17 -> 0.023940841 | E17: =D17*$B$4*SQRT($B$5) -> 23940.841 | F17: =ROUNDUP(B17*$B$20,0) -> 25 | G17: =SMALL($E$25:$E$524,F17) -> -0.024693286 | H17: =-G17*$B$4*SQRT($B$5) -> 24693.286 | I17: =-AVERAGEIF($E$25:$E$524,"<="&C17)*$B$4*SQRT($B$5) -> 36848.666 | K17: Pros
A18: 0.99 | B18: =1-A18 -> 0.01 | C18: =_xlfn.PERCENTILE.INC($E$25:$E$524,B18) -> -0.042713764 | D18: =-C18 -> 0.042713764 | E18: =D18*$B$4*SQRT($B$5) -> 42713.764 | F18: =ROUNDUP(B18*$B$20,0) -> 5 | G18: =SMALL($E$25:$E$524,F18) -> -0.042934862 | H18: =-G18*$B$4*SQRT($B$5) -> 42934.862 | I18: =-AVERAGEIF($E$25:$E$524,"<="&C18)*$B$4*SQRT($B$5) -> 62258.956 | K18: Simple and intuitive; easy to explain to management/regulators.
K19: No normality assumption - captures fat tails, skew and real correlations present in the data.
A20: Number of historical observations (N) | B20: =COUNT($E$25:$E$524) -> 500 | K20: Handles non-linear instruments naturally by full revaluation.
A22: STEP 3: Portfolio daily return = SUMPRODUCT(weights, stock returns); P&L = return x V. STEP 4: sorted with SMALL() | K22: Cons
K23: Completely dependent on the chosen window - events not in history (e.g. a crash) cannot appear.
A24: Date | B24: JPM Return | C24: MS Return | D24: BAC Return | E24: Portfolio Return | F24: Portfolio P&L ($) | G24: Rank | H24: Sorted Port. Return (worst->best) | I24: Sorted P&L ($) | K24: Few observations in the tail, so 99% VaR is based on only a handful of data points (noisy). | L24: Bin (upper, return) | M24: Frequency
A25: =Data!A7 -> 45597 | B25: =Data!F7 -> 0.0045963912 | C25: =Data!G7 -> 0.0051613468 | D25: =Data!H7 -> -0.0014347889 | E25: =B25*$B$7+C25*$B$8+D25*$B$9 -> 0.0027743164 | F25: =E25*$B$4 -> 2774.3164 | G25: 1 | H25: =SMALL($E$25:$E$524,G25) -> -0.091798847 | I25: =H25*$B$4 -> -91798.847 | K25: Slow to react to changes in volatility regime (all days weighted equally). | L25: -0.06 | M25: =COUNTIFS($E$25:$E$524,"<="&L25) -> 2
A26: =Data!A8 -> 45600 | B26: =Data!F8 -> -0.014174387 | C26: =Data!G8 -> -0.0060763397 | D26: =Data!H8 -> -0.010296776 | E26: =B26*$B$7+C26*$B$8+D26*$B$9 -> -0.010182501 | F26: =E26*$B$4 -> -10182.501 | G26: 2 | H26: =SMALL($E$25:$E$524,G26) -> -0.075307155 | I26: =H26*$B$4 -> -75307.155 | K26: Needs a lot of clean historical data. | L26: -0.055 | M26: =COUNTIFS($E$25:$E$524,"<="&L26,$E$25:$E$524,">"&L25) -> 0
A27: =Data!A9 -> 45601 | B27: =Data!F9 -> 0.0077806733 | C27: =Data!G9 -> 0.014379216 | D27: =Data!H9 -> 0.013307212 | E27: =B27*$B$7+C27*$B$8+D27*$B$9 -> 0.011822367 | F27: =E27*$B$4 -> 11822.367 | G27: 3 | H27: =SMALL($E$25:$E$524,G27) -> -0.053535549 | I27: =H27*$B$4 -> -53535.549 | L27: -0.05 | M27: =COUNTIFS($E$25:$E$524,"<="&L27,$E$25:$E$524,">"&L26) -> 1
A28: =Data!A10 -> 45602 | B28: =Data!F10 -> 0.1154452 | C28: =Data!G10 -> 0.11611924 | D28: =Data!H10 -> 0.084288481 | E28: =B28*$B$7+C28*$B$8+D28*$B$9 -> 0.10528431 | F28: =E28*$B$4 -> 105284.31 | G28: 4 | H28: =SMALL($E$25:$E$524,G28) -> -0.047718366 | I28: =H28*$B$4 -> -47718.366 | L28: -0.045 | M28: =COUNTIFS($E$25:$E$524,"<="&L28,$E$25:$E$524,">"&L27) -> 1
A29: =Data!A11 -> 45603 | B29: =Data!F11 -> -0.043228209 | C29: =Data!G11 -> -0.023195701 | D29: =Data!H11 -> -0.014093757 | E29: =B29*$B$7+C29*$B$8+D29*$B$9 -> -0.026839222 | F29: =E29*$B$4 -> -26839.222 | G29: 5 | H29: =SMALL($E$25:$E$524,G29) -> -0.042934862 | I29: =H29*$B$4 -> -42934.862 | L29: -0.04 | M29: =COUNTIFS($E$25:$E$524,"<="&L29,$E$25:$E$524,">"&L28) -> 3
A30: =Data!A12 -> 45604 | B30: =Data!F12 -> 0.0025380943 | C30: =Data!G12 -> 0.0084864483 | D30: =Data!H12 -> 0.0080412177 | E30: =B30*$B$7+C30*$B$8+D30*$B$9 -> 0.0063552534 | F30: =E30*$B$4 -> 6355.2534 | G30: 6 | H30: =SMALL($E$25:$E$524,G30) -> -0.042711531 | I30: =H30*$B$4 -> -42711.531 | L30: -0.035 | M30: =COUNTIFS($E$25:$E$524,"<="&L30,$E$25:$E$524,">"&L29) -> 2
A31: =Data!A13 -> 45607 | B31: =Data!F13 -> 0.0097477553 | C31: =Data!G13 -> 0.030803648 | D31: =Data!H13 -> 0.02105032 | E31: =B31*$B$7+C31*$B$8+D31*$B$9 -> 0.020533908 | F31: =E31*$B$4 -> 20533.908 | G31: 7 | H31: =SMALL($E$25:$E$524,G31) -> -0.040125734 | I31: =H31*$B$4 -> -40125.734 | L31: -0.03 | M31: =COUNTIFS($E$25:$E$524,"<="&L31,$E$25:$E$524,">"&L30) -> 4
A32: =Data!A14 -> 45608 | B32: =Data!F14 -> 0.0011283724 | C32: =Data!G14 -> -0.0090621263 | D32: =Data!H14 -> -0.0047743321 | E32: =B32*$B$7+C32*$B$8+D32*$B$9 -> -0.0042360287 | F32: =E32*$B$4 -> -4236.0287 | G32: 8 | H32: =SMALL($E$25:$E$524,G32) -> -0.037227695 | I32: =H32*$B$4 -> -37227.695 | L32: -0.025 | M32: =COUNTIFS($E$25:$E$524,"<="&L32,$E$25:$E$524,">"&L31) -> 9
A33: =Data!A15 -> 45609 | B33: =Data!F15 -> 0.0066788718 | C33: =Data!G15 -> 0.0034008069 | D33: =Data!H15 -> 0.00021790598 | E33: =B33*$B$7+C33*$B$8+D33*$B$9 -> 0.0034325282 | F33: =E33*$B$4 -> 3432.5282 | G33: 9 | H33: =SMALL($E$25:$E$524,G33) -> -0.035049856 | I33: =H33*$B$4 -> -35049.856 | L33: -0.02 | M33: =COUNTIFS($E$25:$E$524,"<="&L33,$E$25:$E$524,">"&L32) -> 11
A34: =Data!A16 -> 45610 | B34: =Data!F16 -> 0.0029441055 | C34: =Data!G16 -> -0.002485698 | D34: =Data!H16 -> 0.00065409712 | E34: =B34*$B$7+C34*$B$8+D34*$B$9 -> 0.00037083488 | F34: =E34*$B$4 -> 370.83488 | G34: 10 | H34: =SMALL($E$25:$E$524,G34) -> -0.03495718 | I34: =H34*$B$4 -> -34957.18 | L34: -0.015 | M34: =COUNTIFS($E$25:$E$524,"<="&L34,$E$25:$E$524,">"&L33) -> 26
A35: =Data!A17 -> 45611 | B35: =Data!F17 -> 0.014222534 | C35: =Data!G17 -> 0.012308468 | D35: =Data!H17 -> 0.018518552 | E35: =B35*$B$7+C35*$B$8+D35*$B$9 -> 0.015016518 | F35: =E35*$B$4 -> 15016.518 | G35: 11 | H35: =SMALL($E$25:$E$524,G35) -> -0.033317847 | I35: =H35*$B$4 -> -33317.847 | L35: -0.01 | M35: =COUNTIFS($E$25:$E$524,"<="&L35,$E$25:$E$524,">"&L34) -> 26
A36: =Data!A18 -> 45614 | B36: =Data!F18 -> -0.0011414046 | C36: =Data!G18 -> -0.0020884327 | D36: =Data!H18 -> -0.00064178463 | E36: =B36*$B$7+C36*$B$8+D36*$B$9 -> -0.0012905406 | F36: =E36*$B$4 -> -1290.5406 | G36: 12 | H36: =SMALL($E$25:$E$524,G36) -> -0.033268186 | I36: =H36*$B$4 -> -33268.186 | L36: -0.005 | M36: =COUNTIFS($E$25:$E$524,"<="&L36,$E$25:$E$524,">"&L35) -> 57
A37: =Data!A19 -> 45615 | B37: =Data!F19 -> -0.0079174232 | C37: =Data!G19 -> -0.011511558 | D37: =Data!H19 -> -0.0066351799 | E37: =B37*$B$7+C37*$B$8+D37*$B$9 -> -0.0086880537 | F37: =E37*$B$4 -> -8688.0537 | G37: 13 | H37: =SMALL($E$25:$E$524,G37) -> -0.03112819 | I37: =H37*$B$4 -> -31128.19 | L37: 0 | M37: =COUNTIFS($E$25:$E$524,"<="&L37,$E$25:$E$524,">"&L36) -> 69
A38: =Data!A20 -> 45616 | B38: =Data!F20 -> -0.0095026166 | C38: =Data!G20 -> -0.0041590797 | D38: =Data!H20 -> -0.0075413954 | E38: =B38*$B$7+C38*$B$8+D38*$B$9 -> -0.0070676972 | F38: =E38*$B$4 -> -7067.6972 | G38: 14 | H38: =SMALL($E$25:$E$524,G38) -> -0.028739572 | I38: =H38*$B$4 -> -28739.572 | L38: 0.005 | M38: =COUNTIFS($E$25:$E$524,"<="&L38,$E$25:$E$524,">"&L37) -> 106
... A49: =Data!A31 -> 45632 | B49: =Data!F31 -> 0.0076584834 | C49: =Data!G31 -> -0.0027624241 | D49: =Data!H31 -> 0.00021389325 | E49: =B49*$B$7+C49*$B$8+D49*$B$9 -> 0.0017033175 | F49: =E49*$B$4 -> 1703.3175 | G49: 25 | H49: =SMALL($E$25:$E$524,G49) -> -0.024693286 | I49: =H49*$B$4 -> -24693.286 | L49: 0.06 | M49: =COUNTIFS($E$25:$E$524,"<="&L49,$E$25:$E$524,">"&L48) -> 0
A50: =Data!A32 -> 45635 | B50: =Data!F32 -> -0.014351563 | C50: =Data!G32 -> -0.010618718 | D50: =Data!H32 -> -0.017968026 | E50: =B50*$B$7+C50*$B$8+D50*$B$9 -> -0.014312769 | F50: =E50*$B$4 -> -14312.769 | G50: 26 | H50: =SMALL($E$25:$E$524,G50) -> -0.023901239 | I50: =H50*$B$4 -> -23901.239
A51: =Data!A33 -> 45636 | B51: =Data!F33 -> -0.003896509 | C51: =Data!G33 -> -0.013921307 | D51: =Data!H33 -> -0.0034850275 | E51: =B51*$B$7+C51*$B$8+D51*$B$9 -> -0.007100948 | F51: =E51*$B$4 -> -7100.948 | G51: 27 | H51: =SMALL($E$25:$E$524,G51) -> -0.02309756 | I51: =H51*$B$4 -> -23097.56
A52: =Data!A34 -> 45637 | B52: =Data!F34 -> 0.0027588972 | C52: =Data!G34 -> 0.0063096308 | D52: =Data!H34 -> 0.0072132127 | E52: =B52*$B$7+C52*$B$8+D52*$B$9 -> 0.0054272469 | F52: =E52*$B$4 -> 5427.2469 | G52: 28 | H52: =SMALL($E$25:$E$524,G52) -> -0.022789553 | I52: =H52*$B$4 -> -22789.553
A53: =Data!A35 -> 45638 | B53: =Data!F35 -> -0.0082125735 | C53: =Data!G35 -> 0.0025080905 | D53: =Data!H35 -> 0 | E53: =B53*$B$7+C53*$B$8+D53*$B$9 -> -0.0019014943 | F53: =E53*$B$4 -> -1901.4943 | G53: 29 | H53: =SMALL($E$25:$E$524,G53) -> -0.022220235 | I53: =H53*$B$4 -> -22220.235
A54: =Data!A36 -> 45639 | B54: =Data!F36 -> -0.0065830367 | C54: =Data!G36 -> -0.0039872158 | D54: =Data!H36 -> -0.0088977259 | E54: =B54*$B$7+C54*$B$8+D54*$B$9 -> -0.0064893262 | F54: =E54*$B$4 -> -6489.3262 | G54: 30 | H54: =SMALL($E$25:$E$524,G54) -> -0.022101085 | I54: =H54*$B$4 -> -22101.085
A55: =Data!A37 -> 45642 | B55: =Data!F37 -> -0.0015002885 | C55: =Data!G37 -> 0.012794428 | D55: =Data!H37 -> -0.0043790469 | E55: =B55*$B$7+C55*$B$8+D55*$B$9 -> 0.0023050309 | F55: =E55*$B$4 -> 2305.0309 | G55: 31 | H55: =SMALL($E$25:$E$524,G55) -> -0.021741415 | I55: =H55*$B$4 -> -21741.415
A56: =Data!A38 -> 45643 | B56: =Data!F38 -> -0.0050924439 | C56: =Data!G38 -> -0.0099977901 | D56: =Data!H38 -> -0.0092369598 | E56: =B56*$B$7+C56*$B$8+D56*$B$9 -> -0.0081090646 | F56: =E56*$B$4 -> -8109.0646 | G56: 32 | H56: =SMALL($E$25:$E$524,G56) -> -0.021400667 | I56: =H56*$B$4 -> -21400.667
A57: =Data!A39 -> 45644 | B57: =Data!F39 -> -0.033520641 | C57: =Data!G39 -> -0.052450323 | D57: =Data!H39 -> -0.034406238 | E57: =B57*$B$7+C57*$B$8+D57*$B$9 -> -0.040125734 | F57: =E57*$B$4 -> -40125.734 | G57: 33 | H57: =SMALL($E$25:$E$524,G57) -> -0.021165868 | I57: =H57*$B$4 -> -21165.868
A58: =Data!A40 -> 45645 | B58: =Data!F40 -> 0.011242874 | C58: =Data!G40 -> -0.0044612253 | D58: =Data!H40 -> -0.002758625 | E58: =B58*$B$7+C58*$B$8+D58*$B$9 -> 0.0013410079 | F58: =E58*$B$4 -> 1341.0079 | G58: 34 | H58: =SMALL($E$25:$E$524,G58) -> -0.019903575 | I58: =H58*$B$4 -> -19903.575
A59: =Data!A41 -> 45646 | B59: =Data!F41 -> 0.019917553 | C59: =Data!G41 -> 0.024398248 | D59: =Data!H41 -> 0.018211033 | E59: =B59*$B$7+C59*$B$8+D59*$B$9 -> 0.020842278 | F59: =E59*$B$4 -> 20842.278 | G59: 35 | H59: =SMALL($E$25:$E$524,G59) -> -0.019754424 | I59: =H59*$B$4 -> -19754.424
A60: =Data!A42 -> 45649 | B60: =Data!F42 -> 0.0033248389 | C60: =Data!G42 -> 0.0081821099 | D60: =Data!H42 -> -0.006339095 | E60: =B60*$B$7+C60*$B$8+D60*$B$9 -> 0.0017226179 | F60: =E60*$B$4 -> 1722.6179 | G60: 36 | H60: =SMALL($E$25:$E$524,G60) -> -0.01968789 | I60: =H60*$B$4 -> -19687.89
A61: =Data!A43 -> 45650 | B61: =Data!F43 -> 0.016443723 | C61: =Data!G43 -> 0.020972245 | D61: =Data!H43 -> 0.011164323 | E61: =B61*$B$7+C61*$B$8+D61*$B$9 -> 0.01619343 | F61: =E61*$B$4 -> 16193.43 | G61: 37 | H61: =SMALL($E$25:$E$524,G61) -> -0.01953446 | I61: =H61*$B$4 -> -19534.46
... A524: =Data!A506 -> 46325 | B524: =Data!F506 -> -0.019034805 | C524: =Data!G506 -> -0.024093211 | D524: =Data!H506 -> -0.022096228 | E524: =B524*$B$7+C524*$B$8+D524*$B$9 -> -0.021741415 | F524: =E524*$B$4 -> -21741.415 | G524: 500 | H524: =SMALL($E$25:$E$524,G524) -> 0.10528431 | I524: =H524*$B$4 -> 105284.31

Sheet MonteCarlo_Method
A1: VaR - Monte Carlo Simulation Method (correlated, multivariate normal) | K1: Method notes
A3: INPUTS (yellow cells are editable) | K3: Steps performed
A4: Portfolio value ($) | B4: 1000000 | K4: 1. Collect data: daily adjusted closing prices of JPM, MS, BAC from Yahoo Finance (Data sheet).
A5: Holding period (days) | B5: 1 | K5: 2. Calculate returns: daily simple returns for each stock.
A6: Stock | B6: Weight | C6: Position ($) | K6: 3. Estimate parameters from history: mean (AVERAGE), standard deviation (STDEV.S) and covariance matrix (COVARIANCE.S).
A7: JPM (JPMorgan Chase) | B7: 0.33333333 | C7: =$B$4*B7 -> 333333.33 | K7: 4. Cholesky decomposition of the covariance matrix (COV = L x L') so simulated stock returns keep their historical correlations.
A8: MS (Morgan Stanley) | B8: 0.33333333 | C8: =$B$4*B8 -> 333333.33 | K8: 5. Generate 10,000 scenarios: 3 independent standard normals Z = NORM.S.INV(RAND()) per scenario, then correlated returns R = mu + L x Z.
A9: BAC (Bank of America) | B9: 0.33333333 | C9: =$B$4*B9 -> 333333.33 | K9: 6. Portfolio return per scenario = SUMPRODUCT(weights, simulated returns); P&L = return x portfolio value.
A10: Total | B10: =SUM(B7:B9) -> 1 | C10: =SUM(C7:C9) -> 1000000 | K10: 7. VaR = -(1-CI) percentile of the simulated returns x V, for 90% / 95% / 99%. Expected Shortfall shown as bonus.
K11: 8. Re-run (F9) to see simulation noise; more simulations = more stable VaR.
A12: STEP 1-3: Data & returns on 'Data' sheet; mean / std dev / covariance estimated from history
A13: Parameter | B13: JPM | C13: MS | D13: BAC | K13: Assumptions
A14: Mean daily return (mu) | B14: =AVERAGE(Data!$F$7:$F$506) -> 0.0010359072 | C14: =AVERAGE(Data!$G$7:$G$506) -> 0.0012091414 | D14: =AVERAGE(Data!$H$7:$H$506) -> 0.00057279405 | K14: Returns follow the chosen stochastic model - here a multivariate normal distribution with parameters estimated from history.
A15: Std dev daily (sigma) | B15: =_xlfn.STDEV.S(Data!$F$7:$F$506) -> 0.015510582 | C15: =_xlfn.STDEV.S(Data!$G$7:$G$506) -> 0.019376095 | D15: =_xlfn.STDEV.S(Data!$H$7:$H$506) -> 0.015833217 | K15: Mean, volatility and correlations are constant over the horizon.
A16: Covariance matrix | B16: JPM | C16: MS | D16: BAC | K16: The random number generator is good and the number of simulations is large enough for convergence.
A17: JPM | B17: =_xlfn.COVARIANCE.S(Data!$F$7:$F$506,Data!$F$7:$F$506) -> 0.00024057815 | C17: =_xlfn.COVARIANCE.S(Data!$F$7:$F$506,Data!$G$7:$G$506) -> 0.00023059516 | D17: =_xlfn.COVARIANCE.S(Data!$F$7:$F$506,Data!$H$7:$H$506) -> 0.00019348421 | K17: Multi-day VaR scaled by SQRT(T) (or simulate a multi-day path instead).
A18: MS | B18: =_xlfn.COVARIANCE.S(Data!$G$7:$G$506,Data!$F$7:$F$506) -> 0.00023059516 | C18: =_xlfn.COVARIANCE.S(Data!$G$7:$G$506,Data!$G$7:$G$506) -> 0.00037543307 | D18: =_xlfn.COVARIANCE.S(Data!$G$7:$G$506,Data!$H$7:$H$506) -> 0.00023677833
A19: BAC | B19: =_xlfn.COVARIANCE.S(Data!$H$7:$H$506,Data!$F$7:$F$506) -> 0.00019348421 | C19: =_xlfn.COVARIANCE.S(Data!$H$7:$H$506,Data!$G$7:$G$506) -> 0.00023677833 | D19: =_xlfn.COVARIANCE.S(Data!$H$7:$H$506,Data!$H$7:$H$506) -> 0.00025069075 | K19: Pros
K20: Most flexible method - can use any distribution (fat-tailed t, GARCH, jumps) and model complex/non-linear instruments and path dependency.
A21: STEP 4: Cholesky decomposition COV = L x L' (used to make the random shocks correlated) | K21: Generates a full P&L distribution, so ES/CVaR and any percentile are easy to obtain.
A22: L (lower-triangular) | B22: JPM | C22: MS | D22: BAC | K22: Not limited to scenarios that occurred in history.
A23: JPM | B23: =SQRT($B$17) -> 0.015510582 | C23: 0 | D23: 0
A24: MS | B24: =$B$18/$B$23 -> 0.014866957 | C24: =SQRT($C$18-$B$24^2) -> 0.012426047 | D24: 0 | K24: Cons
A25: BAC | B25: =$B$19/$B$23 -> 0.012474336 | C25: =($C$19-$B$25*$B$24)/$C$24 -> 0.004130268 | D25: =SQRT($D$19-$B$25^2-$C$25^2) -> 0.0088330387 | K25: Computationally heavy (many simulations; slow in Excel for large portfolios).
K26: Model risk - results are only as good as the assumed distribution and parameters (here normal, so similar to Var-Cov).
A27: STEP 7: VaR from the simulated distribution VaR = -PERCENTILE.INC(simulated P&L, 1-CI) | K27: Results change between runs (simulation/sampling error).
A28: Confidence level | B28: Tail prob (1-CI) | C28: Simulated percentile return | D28: VaR % (1-day) | E28: VaR $ (x SQRT(T)) | F28: Expected Shortfall (CVaR) $ | K28: More complex to build, validate and explain.
A29: 0.9 | B29: =1-A29 -> 0.1 | C29: =_xlfn.PERCENTILE.INC($H$40:$H$10039,B29) -> -0.019132083 | D29: =-C29 -> 0.019132083 | E29: =D29*$B$4*SQRT($B$5) -> 19132.083 | F29: =-AVERAGEIF($H$40:$H$10039,"<="&C29)*$B$4*SQRT($B$5) -> 26625.375
A30: 0.95 | B30: =1-A30 -> 0.05 | C30: =_xlfn.PERCENTILE.INC($H$40:$H$10039,B30) -> -0.025023054 | D30: =-C30 -> 0.025023054 | E30: =D30*$B$4*SQRT($B$5) -> 25023.054 | F30: =-AVERAGEIF($H$40:$H$10039,"<="&C30)*$B$4*SQRT($B$5) -> 31347.672
A31: 0.99 | B31: =1-A31 -> 0.01 | C31: =_xlfn.PERCENTILE.INC($H$40:$H$10039,B31) -> -0.035552568 | D31: =-C31 -> 0.035552568 | E31: =D31*$B$4*SQRT($B$5) -> 35552.568 | F31: =-AVERAGEIF($H$40:$H$10039,"<="&C31)*$B$4*SQRT($B$5) -> 40549.49
A33: Number of simulations | B33: 10000
A34: Mean of simulated portfolio return (check vs. history) | B34: =AVERAGE($H$40:$H$10039) -> 0.00087266022
A35: Std dev of simulated portfolio return (check) | B35: =_xlfn.STDEV.S($H$40:$H$10039) -> 0.015504529
A36: Press F9 to re-run the simulation (RAND() is volatile) - VaR will move slightly each run.
A38: STEP 5: Random normals Z = NORM.S.INV(RAND()); correlated returns R = mu + L x Z. STEP 6: portfolio return & P&L for each scenario
A39: Sim # | B39: Z1 | C39: Z2 | D39: Z3 | E39: JPM sim return | F39: MS sim return | G39: BAC sim return | H39: Portfolio return | I39: Portfolio P&L ($)
A40: 1 | B40: =_xlfn.NORM.S.INV(RAND()) -> -0.29094838 | C40: =_xlfn.NORM.S.INV(RAND()) -> -2.0656111 | D40: =_xlfn.NORM.S.INV(RAND()) -> -1.6974402 | E40: =$B$14+$B$23*B40 -> -0.0034768716 | F40: =$C$14+$B$24*B40+$C$24*C40 -> -0.028783757 | G40: =$D$14+$B$25*B40+$C$25*C40+$D$25*D40 -> -0.026581677 | H40: =E40*$B$7+F40*$B$8+G40*$B$9 -> -0.019614102 | I40: =H40*$B$4 -> -19614.102
A41: 2 | B41: =_xlfn.NORM.S.INV(RAND()) -> -0.95557978 | C41: =_xlfn.NORM.S.INV(RAND()) -> 1.1691812 | D41: =_xlfn.NORM.S.INV(RAND()) -> 1.248454 | E41: =$B$14+$B$23*B41 -> -0.013785691 | F41: =$C$14+$B$24*B41+$C$24*C41 -> 0.0015308793 | G41: =$D$14+$B$25*B41+$C$25*C41+$D$25*D41 -> 0.0045092452 | H41: =E41*$B$7+F41*$B$8+G41*$B$9 -> -0.0025818556 | I41: =H41*$B$4 -> -2581.8556
A42: 3 | B42: =_xlfn.NORM.S.INV(RAND()) -> -1.5005921 | C42: =_xlfn.NORM.S.INV(RAND()) -> -0.93402864 | D42: =_xlfn.NORM.S.INV(RAND()) -> -0.77962476 | E42: =$B$14+$B$23*B42 -> -0.022239149 | F42: =$C$14+$B$24*B42+$C$24*C42 -> -0.032706381 | G42: =$D$14+$B$25*B42+$C$25*C42+$D$25*D42 -> -0.02889034 | H42: =E42*$B$7+F42*$B$8+G42*$B$9 -> -0.02794529 | I42: =H42*$B$4 -> -27945.29
A43: 4 | B43: =_xlfn.NORM.S.INV(RAND()) -> 0.83394366 | C43: =_xlfn.NORM.S.INV(RAND()) -> -3.0104799 | D43: =_xlfn.NORM.S.INV(RAND()) -> 1.2487577 | E43: =$B$14+$B$23*B43 -> 0.013970859 | F43: =$C$14+$B$24*B43+$C$24*C43 -> -0.02380102 | G43: =$D$14+$B$25*B43+$C$25*C43+$D$25*D43 -> 0.009571924 | H43: =E43*$B$7+F43*$B$8+G43*$B$9 -> -8.6079142e-05 | I43: =H43*$B$4 -> -86.079142
A44: 5 | B44: =_xlfn.NORM.S.INV(RAND()) -> 0.95197225 | C44: =_xlfn.NORM.S.INV(RAND()) -> 0.085704528 | D44: =_xlfn.NORM.S.INV(RAND()) -> 0.40551811 | E44: =$B$14+$B$23*B44 -> 0.015801551 | F44: =$C$14+$B$24*B44+$C$24*C44 -> 0.016427041 | G44: =$D$14+$B$25*B44+$C$25*C44+$D$25*D44 -> 0.016383956 | H44: =E44*$B$7+F44*$B$8+G44*$B$9 -> 0.016204182 | I44: =H44*$B$4 -> 16204.182
A45: 6 | B45: =_xlfn.NORM.S.INV(RAND()) -> -0.32172219 | C45: =_xlfn.NORM.S.INV(RAND()) -> -0.44096902 | D45: =_xlfn.NORM.S.INV(RAND()) -> 1.8610665 | E45: =$B$14+$B$23*B45 -> -0.0039541913 | F45: =$C$14+$B$24*B45+$C$24*C45 -> -0.0090533907 | G45: =$D$14+$B$25*B45+$C$25*C45+$D$25*D45 -> 0.011177075 | H45: =E45*$B$7+F45*$B$8+G45*$B$9 -> -0.00061016893 | I45: =H45*$B$4 -> -610.16893
A46: 7 | B46: =_xlfn.NORM.S.INV(RAND()) -> 1.9799423 | C46: =_xlfn.NORM.S.INV(RAND()) -> 1.0758285 | D46: =_xlfn.NORM.S.INV(RAND()) -> -0.26414057 | E46: =$B$14+$B$23*B46 -> 0.031745965 | F46: =$C$14+$B$24*B46+$C$24*C46 -> 0.044013156 | G46: =$D$14+$B$25*B46+$C$25*C46+$D$25*D46 -> 0.027381556 | H46: =E46*$B$7+F46*$B$8+G46*$B$9 -> 0.034380226 | I46: =H46*$B$4 -> 34380.226
A47: 8 | B47: =_xlfn.NORM.S.INV(RAND()) -> -1.4078473 | C47: =_xlfn.NORM.S.INV(RAND()) -> 0.088450862 | D47: =_xlfn.NORM.S.INV(RAND()) -> -1.3531938 | E47: =$B$14+$B$23*B47 -> -0.020800623 | F47: =$C$14+$B$24*B47+$C$24*C47 -> -0.018622169 | G47: =$D$14+$B$25*B47+$C$25*C47+$D$25*D47 -> -0.028576653 | H47: =E47*$B$7+F47*$B$8+G47*$B$9 -> -0.022666482 | I47: =H47*$B$4 -> -22666.482
A48: 9 | B48: =_xlfn.NORM.S.INV(RAND()) -> 0.13600934 | C48: =_xlfn.NORM.S.INV(RAND()) -> -1.0008872 | D48: =_xlfn.NORM.S.INV(RAND()) -> 1.6054842 | E48: =$B$14+$B$23*B48 -> 0.0031454913 | F48: =$C$14+$B$24*B48+$C$24*C48 -> -0.0092058857 | G48: =$D$14+$B$25*B48+$C$25*C48+$D$25*D48 -> 0.012316792 | H48: =E48*$B$7+F48*$B$8+G48*$B$9 -> 0.002085466 | I48: =H48*$B$4 -> 2085.466
A49: 10 | B49: =_xlfn.NORM.S.INV(RAND()) -> 0.83665251 | C49: =_xlfn.NORM.S.INV(RAND()) -> -0.53494217 | D49: =_xlfn.NORM.S.INV(RAND()) -> 2.2352164 | E49: =$B$14+$B$23*B49 -> 0.014012875 | F49: =$C$14+$B$24*B49+$C$24*C49 -> 0.0070004016 | G49: =$D$14+$B$25*B49+$C$25*C49+$D$25*D49 -> 0.028543777 | H49: =E49*$B$7+F49*$B$8+G49*$B$9 -> 0.016519018 | I49: =H49*$B$4 -> 16519.018
A50: 11 | B50: =_xlfn.NORM.S.INV(RAND()) -> 1.0895378 | C50: =_xlfn.NORM.S.INV(RAND()) -> -0.16280217 | D50: =_xlfn.NORM.S.INV(RAND()) -> 0.54218269 | E50: =$B$14+$B$23*B50 -> 0.017935272 | F50: =$C$14+$B$24*B50+$C$24*C50 -> 0.015384265 | G50: =$D$14+$B$25*B50+$C$25*C50+$D$25*D50 -> 0.018280759 | H50: =E50*$B$7+F50*$B$8+G50*$B$9 -> 0.017200099 | I50: =H50*$B$4 -> 17200.099
A51: 12 | B51: =_xlfn.NORM.S.INV(RAND()) -> -0.99554817 | C51: =_xlfn.NORM.S.INV(RAND()) -> 0.2123704 | D51: =_xlfn.NORM.S.INV(RAND()) -> -0.61390219 | E51: =$B$14+$B$23*B51 -> -0.014405624 | F51: =$C$14+$B$24*B51+$C$24*C51 -> -0.010952706 | G51: =$D$14+$B$25*B51+$C$25*C51+$D$25*D51 -> -0.016391484 | H51: =E51*$B$7+F51*$B$8+G51*$B$9 -> -0.013916605 | I51: =H51*$B$4 -> -13916.605
... A10039: 10000 | B10039: =_xlfn.NORM.S.INV(RAND()) -> 1.350452 | C10039: =_xlfn.NORM.S.INV(RAND()) -> 1.0223522 | D10039: =_xlfn.NORM.S.INV(RAND()) -> -0.97837101 | E10039: =$B$14+$B$23*B10039 -> 0.021982203 | F10039: =$C$14+$B$24*B10039+$C$24*C10039 -> 0.03399005 | G10039: =$D$14+$B$25*B10039+$C$25*C10039+$D$25*D10039 -> 0.012999385 | H10039: =E10039*$B$7+F10039*$B$8+G10039*$B$9 -> 0.022990546 | I10039: =H10039*$B$4 -> 22990.546

Sheet Backtesting
A1: VaR Backtesting - Rolling out-of-sample VaR, Basel Traffic Light & Kupiec POF test | Z1: Backtesting notes
A3: INPUTS | Z3: Steps performed
A4: Estimation window (days) | B4: 250 | Z4: 1. Collect data & returns (Data sheet); daily portfolio return taken from Historical_Method (same weights).
A5: Portfolio value ($) - from Historical sheet | B5: =Historical_Method!$B$4 -> 1000000 | Z5: 2. Rolling window: for each test day, VaR is estimated using ONLY the previous 250 days (no look-ahead). First 250 days are the initial estimation window, the remaining 250 days are the out-of-sample test period.
A6: Kupiec test significance level | B6: 0.05 | Z6: - Var-Cov: (Z x STDEV.S(window) - AVERAGE(window)) x V (STDEV of portfolio returns = SQRT(w'COVw) of the window)
A7: Chi-square(1) critical value =CHISQ.INV.RT(sig,1) | B7: =_xlfn.CHISQ.INV.RT(B6,1) -> 3.8414588 | Z7: - Historical: -PERCENTILE.INC(window, 1-CI) x V
A8: Weights: taken from Historical_Method sheet (portfolio returns column) | Z8: - Monte Carlo: -(mu + sigma x simulated Z-quantile) x V, using 10,000 fixed N(0,1) draws in column AN (common random numbers). Python version simulates all 3 stocks with Cholesky every day, so its MC numbers may differ slightly.
Z9: 3. Exception (breach) = 1 if actual loss (-P&L) > VaR forecast for that day (highlighted red).
A10: Z-scores: analytic (Var-Cov) and simulated quantile of 10,000 fixed N(0,1) draws (Monte Carlo) | Z10: 4. Count exceptions x over T test days; expected = (1-CI) x T.
A11: Confidence level | B11: Analytic Z =NORM.S.INV(CI) | C11: Simulated Z-quantile (1-CI) | Z11: 5. Traffic Light: cumulative binomial P(X<=x) = BINOM.DIST(x,T,p,TRUE). Green < 95%, Yellow 95%-99.99%, Red >= 99.99%. At 99%/250 days = Basel's 0-4 / 5-9 / 10+.
A12: 0.9 | B12: =_xlfn.NORM.S.INV(A12) -> 1.2815516 | C12: =_xlfn.PERCENTILE.INC($AN$31:$AN$10030,1-A12) -> -1.3137682 | Z12: 6. Kupiec POF test: LR = -2ln[(1-p)^(T-x) p^x] + 2ln[(1-x/T)^(T-x) (x/T)^x] ~ chi-square(1). Reject the model if LR > 3.841 (p-value < 5%).
A13: 0.95 | B13: =_xlfn.NORM.S.INV(A13) -> 1.6448536 | C13: =_xlfn.PERCENTILE.INC($AN$31:$AN$10030,1-A13) -> -1.6740935
A14: 0.99 | B14: =_xlfn.NORM.S.INV(A14) -> 2.3263479 | C14: =_xlfn.PERCENTILE.INC($AN$31:$AN$10030,1-A14) -> -2.3738112 | Z14: Assumptions
Z15: Exceptions are independent Bernoulli(p) events - Kupiec ignores whether breaches cluster together.
A16: STEP 4-6: Exception count, Kupiec POF test & Traffic Light zone | Z16: Portfolio composition is constant over the test period; P&L is the clean (hypothetical) P&L of that portfolio.
A17: Method | B17: CI | C17: Test days (T) | D17: Expected exc. (p*T) | E17: Actual exc. (x) | F17: Exception rate | G17: Kupiec LR | H17: p-value =CHISQ.DIST.RT | I17: Kupiec result | J17: Cum. binomial P(X<=x) | K17: Traffic light zone | L17: Basel plus factor (99% only) | Z17: 250 test days is enough to judge the model (in practice power is low, especially at 99%).
A18: Variance-Covariance | B18: 0.9 | C18: =COUNT(D281:D530) -> 250 | D18: =(1-B18)*C18 -> 25 | E18: =SUM(E281:E530) -> 24 | F18: =E18/C18 -> 0.096 | G18: =-2*((C18-E18)*LN(B18)+E18*LN(1-B18))+2*(IF(E18<C18,(C18-E18)*LN(1-F18),0)+IF(E18>0,E18*LN(F18),0)) -> 0.044982138 | H18: =_xlfn.CHISQ.DIST.RT(G18,1) -> 0.83203688 | I18: =IF(G18>$B$7,"Reject","Accept") -> Accept | J18: =_xlfn.BINOM.DIST(E18,C18,1-B18,TRUE) -> 0.46917356 | K18: =IF(J18<0.95,"GREEN",IF(J18<0.9999,"YELLOW","RED")) -> GREEN | L18: n/a
A19: Variance-Covariance | B19: 0.95 | C19: =COUNT(F281:F530) -> 250 | D19: =(1-B19)*C19 -> 12.5 | E19: =SUM(G281:G530) -> 15 | F19: =E19/C19 -> 0.06 | G19: =-2*((C19-E19)*LN(B19)+E19*LN(1-B19))+2*(IF(E19<C19,(C19-E19)*LN(1-F19),0)+IF(E19>0,E19*LN(F19),0)) -> 0.49605532 | H19: =_xlfn.CHISQ.DIST.RT(G19,1) -> 0.48123853 | I19: =IF(G19>$B$7,"Reject","Accept") -> Accept | J19: =_xlfn.BINOM.DIST(E19,C19,1-B19,TRUE) -> 0.81128084 | K19: =IF(J19<0.95,"GREEN",IF(J19<0.9999,"YELLOW","RED")) -> GREEN | L19: n/a | Z19: Pros
A20: Variance-Covariance | B20: 0.99 | C20: =COUNT(H281:H530) -> 250 | D20: =(1-B20)*C20 -> 2.5 | E20: =SUM(I281:I530) -> 5 | F20: =E20/C20 -> 0.02 | G20: =-2*((C20-E20)*LN(B20)+E20*LN(1-B20))+2*(IF(E20<C20,(C20-E20)*LN(1-F20),0)+IF(E20>0,E20*LN(F20),0)) -> 1.9568098 | H20: =_xlfn.CHISQ.DIST.RT(G20,1) -> 0.16185492 | I20: =IF(G20>$B$7,"Reject","Accept") -> Accept | J20: =_xlfn.BINOM.DIST(E20,C20,1-B20,TRUE) -> 0.95881682 | K20: =IF(J20<0.95,"GREEN",IF(J20<0.9999,"YELLOW","RED")) -> YELLOW | L20: =IF(C20<>250,"n/a",IF(E20<=4,0,IF(E20>=10,1,CHOOSE(E20-4,0.4,0.5,0.65,0.75,0.85)))) -> 0.4 | Z20: Traffic Light: simple, regulatory standard (Basel), directly sets the capital multiplier.
A21: Historical | B21: 0.9 | C21: =COUNT(J281:J530) -> 250 | D21: =(1-B21)*C21 -> 25 | E21: =SUM(K281:K530) -> 31 | F21: =E21/C21 -> 0.124 | G21: =-2*((C21-E21)*LN(B21)+E21*LN(1-B21))+2*(IF(E21<C21,(C21-E21)*LN(1-F21),0)+IF(E21>0,E21*LN(F21),0)) -> 1.498347 | H21: =_xlfn.CHISQ.DIST.RT(G21,1) -> 0.22092587 | I21: =IF(G21>$B$7,"Reject","Accept") -> Accept | J21: =_xlfn.BINOM.DIST(E21,C21,1-B21,TRUE) -> 0.91142201 | K21: =IF(J21<0.95,"GREEN",IF(J21<0.9999,"YELLOW","RED")) -> GREEN | L21: n/a | Z21: Kupiec: formal hypothesis test that penalises both too many AND too few exceptions (over-conservative models fail too).
A22: Historical | B22: 0.95 | C22: =COUNT(L281:L530) -> 250 | D22: =(1-B22)*C22 -> 12.5 | E22: =SUM(M281:M530) -> 14 | F22: =E22/C22 -> 0.056 | G22: =-2*((C22-E22)*LN(B22)+E22*LN(1-B22))+2*(IF(E22<C22,(C22-E22)*LN(1-F22),0)+IF(E22>0,E22*LN(F22),0)) -> 0.18269688 | H22: =_xlfn.CHISQ.DIST.RT(G22,1) -> 0.66906576 | I22: =IF(G22>$B$7,"Reject","Accept") -> Accept | J22: =_xlfn.BINOM.DIST(E22,C22,1-B22,TRUE) -> 0.72883631 | K22: =IF(J22<0.95,"GREEN",IF(J22<0.9999,"YELLOW","RED")) -> GREEN | L22: n/a | Z22: Out-of-sample rolling design mimics how a risk desk actually uses VaR each day.
A23: Historical | B23: 0.99 | C23: =COUNT(N281:N530) -> 250 | D23: =(1-B23)*C23 -> 2.5 | E23: =SUM(O281:O530) -> 2 | F23: =E23/C23 -> 0.008 | G23: =-2*((C23-E23)*LN(B23)+E23*LN(1-B23))+2*(IF(E23<C23,(C23-E23)*LN(1-F23),0)+IF(E23>0,E23*LN(F23),0)) -> 0.10843522 | H23: =_xlfn.CHISQ.DIST.RT(G23,1) -> 0.7419327 | I23: =IF(G23>$B$7,"Reject","Accept") -> Accept | J23: =_xlfn.BINOM.DIST(E23,C23,1-B23,TRUE) -> 0.54316897 | K23: =IF(J23<0.95,"GREEN",IF(J23<0.9999,"YELLOW","RED")) -> GREEN | L23: =IF(C23<>250,"n/a",IF(E23<=4,0,IF(E23>=10,1,CHOOSE(E23-4,0.4,0.5,0.65,0.75,0.85)))) -> 0
A24: Monte Carlo | B24: 0.9 | C24: =COUNT(P281:P530) -> 250 | D24: =(1-B24)*C24 -> 25 | E24: =SUM(Q281:Q530) -> 23 | F24: =E24/C24 -> 0.092 | G24: =-2*((C24-E24)*LN(B24)+E24*LN(1-B24))+2*(IF(E24<C24,(C24-E24)*LN(1-F24),0)+IF(E24>0,E24*LN(F24),0)) -> 0.18217132 | H24: =_xlfn.CHISQ.DIST.RT(G24,1) -> 0.66951384 | I24: =IF(G24>$B$7,"Reject","Accept") -> Accept | J24: =_xlfn.BINOM.DIST(E24,C24,1-B24,TRUE) -> 0.385723 | K24: =IF(J24<0.95,"GREEN",IF(J24<0.9999,"YELLOW","RED")) -> GREEN | L24: n/a | Z24: Cons
A25: Monte Carlo | B25: 0.95 | C25: =COUNT(R281:R530) -> 250 | D25: =(1-B25)*C25 -> 12.5 | E25: =SUM(S281:S530) -> 13 | F25: =E25/C25 -> 0.052 | G25: =-2*((C25-E25)*LN(B25)+E25*LN(1-B25))+2*(IF(E25<C25,(C25-E25)*LN(1-F25),0)+IF(E25>0,E25*LN(F25),0)) -> 0.020791913 | H25: =_xlfn.CHISQ.DIST.RT(G25,1) -> 0.88534727 | I25: =IF(G25>$B$7,"Reject","Accept") -> Accept | J25: =_xlfn.BINOM.DIST(E25,C25,1-B25,TRUE) -> 0.62927406 | K25: =IF(J25<0.95,"GREEN",IF(J25<0.9999,"YELLOW","RED")) -> GREEN | L25: n/a | Z25: Both tests only use the COUNT of exceptions - not their timing (use Christoffersen independence test) or size (use ES backtests).
A26: Monte Carlo | B26: 0.99 | C26: =COUNT(T281:T530) -> 250 | D26: =(1-B26)*C26 -> 2.5 | E26: =SUM(U281:U530) -> 4 | F26: =E26/C26 -> 0.016 | G26: =-2*((C26-E26)*LN(B26)+E26*LN(1-B26))+2*(IF(E26<C26,(C26-E26)*LN(1-F26),0)+IF(E26>0,E26*LN(F26),0)) -> 0.76913836 | H26: =_xlfn.CHISQ.DIST.RT(G26,1) -> 0.38048374 | I26: =IF(G26>$B$7,"Reject","Accept") -> Accept | J26: =_xlfn.BINOM.DIST(E26,C26,1-B26,TRUE) -> 0.89218763 | K26: =IF(J26<0.95,"GREEN",IF(J26<0.9999,"YELLOW","RED")) -> GREEN | L26: =IF(C26<>250,"n/a",IF(E26<=4,0,IF(E26>=10,1,CHOOSE(E26-4,0.4,0.5,0.65,0.75,0.85)))) -> 0 | Z26: Low statistical power with 250 observations: a poor 99% model can easily pass.
A27: Basel 99%/250-day table: Green 0-4 exceptions (multiplier 3.0), Yellow 5-9 (3.40/3.50/3.65/3.75/3.85), Red 10+ (4.0). Zones here use the same cumulative-binomial cut-offs (95% / 99.99%) so they apply to every CI. | Z27: Results depend on window length and the specific test period chosen.
A29: STEP 1-3: Daily portfolio P&L, rolling VaR forecast from the PREVIOUS 250 days only, exception = 1 if loss > VaR
A30: Date | B30: Portfolio return | C30: Actual P&L ($) | D30: VC VaR 90% | E30: VC Exc 90% | F30: VC VaR 95% | G30: VC Exc 95% | H30: VC VaR 99% | I30: VC Exc 99% | J30: HS VaR 90% | K30: HS Exc 90% | L30: HS VaR 95% | M30: HS Exc 95% | N30: HS VaR 99% | O30: HS Exc 99% | P30: MC VaR 90% | Q30: MC Exc 90% | R30: MC VaR 95% | S30: MC Exc 95% | T30: MC VaR 99% | U30: MC Exc 99% | V30: -VC VaR 99% (chart) | W30: -HS VaR 99% (chart) | X30: -MC VaR 99% (chart) | AN30: MC fixed N(0,1) draws (seed 42)
A31: =Historical_Method!A25 -> 45597 | B31: =Historical_Method!E25 -> 0.0027743164 | C31: =B31*$B$5 -> 2774.3164 | AN31: 0.30471708
A32: =Historical_Method!A26 -> 45600 | B32: =Historical_Method!E26 -> -0.010182501 | C32: =B32*$B$5 -> -10182.501 | AN32: -1.0399841
A33: =Historical_Method!A27 -> 45601 | B33: =Historical_Method!E27 -> 0.011822367 | C33: =B33*$B$5 -> 11822.367 | AN33: 0.7504512
A34: =Historical_Method!A28 -> 45602 | B34: =Historical_Method!E28 -> 0.10528431 | C34: =B34*$B$5 -> 105284.31 | AN34: 0.94056472
A35: =Historical_Method!A29 -> 45603 | B35: =Historical_Method!E29 -> -0.026839222 | C35: =B35*$B$5 -> -26839.222 | AN35: -1.9510352
A36: =Historical_Method!A30 -> 45604 | B36: =Historical_Method!E30 -> 0.0063552534 | C36: =B36*$B$5 -> 6355.2534 | AN36: -1.3021795
A37: =Historical_Method!A31 -> 45607 | B37: =Historical_Method!E31 -> 0.020533908 | C37: =B37*$B$5 -> 20533.908 | AN37: 0.1278404
A38: =Historical_Method!A32 -> 45608 | B38: =Historical_Method!E32 -> -0.0042360287 | C38: =B38*$B$5 -> -4236.0287 | AN38: -0.31624259
A39: =Historical_Method!A33 -> 45609 | B39: =Historical_Method!E33 -> 0.0034325282 | C39: =B39*$B$5 -> 3432.5282 | AN39: -0.016801158
A40: =Historical_Method!A34 -> 45610 | B40: =Historical_Method!E34 -> 0.00037083488 | C40: =B40*$B$5 -> 370.83488 | AN40: -0.85304393
A41: =Historical_Method!A35 -> 45611 | B41: =Historical_Method!E35 -> 0.015016518 | C41: =B41*$B$5 -> 15016.518 | AN41: 0.87939797
A42: =Historical_Method!A36 -> 45614 | B42: =Historical_Method!E36 -> -0.0012905406 | C42: =B42*$B$5 -> -1290.5406 | AN42: 0.77779194
... A280: =Historical_Method!A274 -> 45961 | B280: =Historical_Method!E274 -> 0.0039221557 | C280: =B280*$B$5 -> 3922.1557 | AN280: -1.1715666
A281: =Historical_Method!A275 -> 45964 | B281: =Historical_Method!E275 -> -0.0019218049 | C281: =B281*$B$5 -> -1921.8049 | D281: =($B$12*_xlfn.STDEV.S($B31:$B280)-AVERAGE($B31:$B280))*$B$5 -> 20885.35 | E281: =IF(-C281>D281,1,0) -> 0 | F281: =($B$13*_xlfn.STDEV.S($B31:$B280)-AVERAGE($B31:$B280))*$B$5 -> 27232.345 | G281: =IF(-C281>F281,1,0) -> 0 | H281: =($B$14*_xlfn.STDEV.S($B31:$B280)-AVERAGE($B31:$B280))*$B$5 -> 39138.25 | I281: =IF(-C281>H281,1,0) -> 0 | J281: =-_xlfn.PERCENTILE.INC($B31:$B280,1-0.9)*$B$5 -> 14518.866 | K281: =IF(-C281>J281,1,0) -> 0 | L281: =-_xlfn.PERCENTILE.INC($B31:$B280,1-0.95)*$B$5 -> 24937.292 | M281: =IF(-C281>L281,1,0) -> 0 | N281: =-_xlfn.PERCENTILE.INC($B31:$B280,1-0.99)*$B$5 -> 50685.129 | O281: =IF(-C281>N281,1,0) -> 0 | P281: =-(AVERAGE($B31:$B280)+_xlfn.STDEV.S($B31:$B280)*$C$12)*$B$5 -> 21448.185 | Q281: =IF(-C281>P281,1,0) -> 0 | R281: =-(AVERAGE($B31:$B280)+_xlfn.STDEV.S($B31:$B280)*$C$13)*$B$5 -> 27743.174 | S281: =IF(-C281>R281,1,0) -> 0 | T281: =-(AVERAGE($B31:$B280)+_xlfn.STDEV.S($B31:$B280)*$C$14)*$B$5 -> 39967.448 | U281: =IF(-C281>T281,1,0) -> 0 | V281: =-H281 -> -39138.25 | W281: =-N281 -> -50685.129 | X281: =-T281 -> -39967.448 | AN281: -0.36824896
A282: =Historical_Method!A276 -> 45965 | B282: =Historical_Method!E276 -> 0.00050112274 | C282: =B282*$B$5 -> 501.12274 | D282: =($B$12*_xlfn.STDEV.S($B32:$B281)-AVERAGE($B32:$B281))*$B$5 -> 20905.613 | E282: =IF(-C282>D282,1,0) -> 0 | F282: =($B$13*_xlfn.STDEV.S($B32:$B281)-AVERAGE($B32:$B281))*$B$5 -> 27253.026 | G282: =IF(-C282>F282,1,0) -> 0 | H282: =($B$14*_xlfn.STDEV.S($B32:$B281)-AVERAGE($B32:$B281))*$B$5 -> 39159.717 | I282: =IF(-C282>H282,1,0) -> 0 | J282: =-_xlfn.PERCENTILE.INC($B32:$B281,1-0.9)*$B$5 -> 14518.866 | K282: =IF(-C282>J282,1,0) -> 0 | L282: =-_xlfn.PERCENTILE.INC($B32:$B281,1-0.95)*$B$5 -> 24937.292 | M282: =IF(-C282>L282,1,0) -> 0 | N282: =-_xlfn.PERCENTILE.INC($B32:$B281,1-0.99)*$B$5 -> 50685.129 | O282: =IF(-C282>N282,1,0) -> 0 | P282: =-(AVERAGE($B32:$B281)+_xlfn.STDEV.S($B32:$B281)*$C$12)*$B$5 -> 21468.484 | Q282: =IF(-C282>P282,1,0) -> 0 | R282: =-(AVERAGE($B32:$B281)+_xlfn.STDEV.S($B32:$B281)*$C$13)*$B$5 -> 27763.888 | S282: =IF(-C282>R282,1,0) -> 0 | T282: =-(AVERAGE($B32:$B281)+_xlfn.STDEV.S($B32:$B281)*$C$14)*$B$5 -> 39988.97 | U282: =IF(-C282>T282,1,0) -> 0 | V282: =-H282 -> -39159.717 | W282: =-N282 -> -50685.129 | X282: =-T282 -> -39988.97 | AN282: 0.34155555
A283: =Historical_Method!A277 -> 45966 | B283: =Historical_Method!E277 -> -0.0017891164 | C283: =B283*$B$5 -> -1789.1164 | D283: =($B$12*_xlfn.STDEV.S($B33:$B282)-AVERAGE($B33:$B282))*$B$5 -> 20842.894 | E283: =IF(-C283>D283,1,0) -> 0 | F283: =($B$13*_xlfn.STDEV.S($B33:$B282)-AVERAGE($B33:$B282))*$B$5 -> 27184.642 | G283: =IF(-C283>F283,1,0) -> 0 | H283: =($B$14*_xlfn.STDEV.S($B33:$B282)-AVERAGE($B33:$B282))*$B$5 -> 39080.706 | I283: =IF(-C283>H283,1,0) -> 0 | J283: =-_xlfn.PERCENTILE.INC($B33:$B282,1-0.9)*$B$5 -> 14518.866 | K283: =IF(-C283>J283,1,0) -> 0 | L283: =-_xlfn.PERCENTILE.INC($B33:$B282,1-0.95)*$B$5 -> 24937.292 | M283: =IF(-C283>L283,1,0) -> 0 | N283: =-_xlfn.PERCENTILE.INC($B33:$B282,1-0.99)*$B$5 -> 50685.129 | O283: =IF(-C283>N283,1,0) -> 0 | P283: =-(AVERAGE($B33:$B282)+_xlfn.STDEV.S($B33:$B282)*$C$12)*$B$5 -> 21405.263 | Q283: =IF(-C283>P283,1,0) -> 0 | R283: =-(AVERAGE($B33:$B282)+_xlfn.STDEV.S($B33:$B282)*$C$13)*$B$5 -> 27695.048 | S283: =IF(-C283>R283,1,0) -> 0 | T283: =-(AVERAGE($B33:$B282)+_xlfn.STDEV.S($B33:$B282)*$C$14)*$B$5 -> 39909.218 | U283: =IF(-C283>T283,1,0) -> 0 | V283: =-H283 -> -39080.706 | W283: =-N283 -> -50685.129 | X283: =-T283 -> -39909.218 | AN283: 1.7286976
A284: =Historical_Method!A278 -> 45967 | B284: =Historical_Method!E278 -> 0.0036476629 | C284: =B284*$B$5 -> 3647.6629 | D284: =($B$12*_xlfn.STDEV.S($B34:$B283)-AVERAGE($B34:$B283))*$B$5 -> 20883.224 | E284: =IF(-C284>D284,1,0) -> 0 | F284: =($B$13*_xlfn.STDEV.S($B34:$B283)-AVERAGE($B34:$B283))*$B$5 -> 27220.97 | G284: =IF(-C284>F284,1,0) -> 0 | H284: =($B$14*_xlfn.STDEV.S($B34:$B283)-AVERAGE($B34:$B283))*$B$5 -> 39109.528 | I284: =IF(-C284>H284,1,0) -> 0 | J284: =-_xlfn.PERCENTILE.INC($B34:$B283,1-0.9)*$B$5 -> 14518.866 | K284: =IF(-C284>J284,1,0) -> 0 | L284: =-_xlfn.PERCENTILE.INC($B34:$B283,1-0.95)*$B$5 -> 24937.292 | M284: =IF(-C284>L284,1,0) -> 0 | N284: =-_xlfn.PERCENTILE.INC($B34:$B283,1-0.99)*$B$5 -> 50685.129 | O284: =IF(-C284>N284,1,0) -> 0 | P284: =-(AVERAGE($B34:$B283)+_xlfn.STDEV.S($B34:$B283)*$C$12)*$B$5 -> 21445.238 | Q284: =IF(-C284>P284,1,0) -> 0 | R284: =-(AVERAGE($B34:$B283)+_xlfn.STDEV.S($B34:$B283)*$C$13)*$B$5 -> 27731.055 | S284: =IF(-C284>R284,1,0) -> 0 | T284: =-(AVERAGE($B34:$B283)+_xlfn.STDEV.S($B34:$B283)*$C$14)*$B$5 -> 39937.518 | U284: =IF(-C284>T284,1,0) -> 0 | V284: =-H284 -> -39109.528 | W284: =-N284 -> -50685.129 | X284: =-T284 -> -39937.518 | AN284: -0.98685708
A285: =Historical_Method!A279 -> 45968 | B285: =Historical_Method!E279 -> -0.0018849069 | C285: =B285*$B$5 -> -1884.9069 | D285: =($B$12*_xlfn.STDEV.S($B35:$B284)-AVERAGE($B35:$B284))*$B$5 -> 19633.259 | E285: =IF(-C285>D285,1,0) -> 0 | F285: =($B$13*_xlfn.STDEV.S($B35:$B284)-AVERAGE($B35:$B284))*$B$5 -> 25501.407 | G285: =IF(-C285>F285,1,0) -> 0 | H285: =($B$14*_xlfn.STDEV.S($B35:$B284)-AVERAGE($B35:$B284))*$B$5 -> 36509.077 | I285: =IF(-C285>H285,1,0) -> 0 | J285: =-_xlfn.PERCENTILE.INC($B35:$B284,1-0.9)*$B$5 -> 14518.866 | K285: =IF(-C285>J285,1,0) -> 0 | L285: =-_xlfn.PERCENTILE.INC($B35:$B284,1-0.95)*$B$5 -> 24937.292 | M285: =IF(-C285>L285,1,0) -> 0 | N285: =-_xlfn.PERCENTILE.INC($B35:$B284,1-0.99)*$B$5 -> 50685.129 | O285: =IF(-C285>N285,1,0) -> 0 | P285: =-(AVERAGE($B35:$B284)+_xlfn.STDEV.S($B35:$B284)*$C$12)*$B$5 -> 20153.63 | Q285: =IF(-C285>P285,1,0) -> 0 | R285: =-(AVERAGE($B35:$B284)+_xlfn.STDEV.S($B35:$B284)*$C$13)*$B$5 -> 25973.697 | S285: =IF(-C285>R285,1,0) -> 0 | T285: =-(AVERAGE($B35:$B284)+_xlfn.STDEV.S($B35:$B284)*$C$14)*$B$5 -> 37275.717 | U285: =IF(-C285>T285,1,0) -> 0 | V285: =-H285 -> -36509.077 | W285: =-N285 -> -50685.129 | X285: =-T285 -> -37275.717 | AN285: -0.24527785
A286: =Historical_Method!A280 -> 45971 | B286: =Historical_Method!E280 -> 0.0097443085 | C286: =B286*$B$5 -> 9744.3085 | D286: =($B$12*_xlfn.STDEV.S($B36:$B285)-AVERAGE($B36:$B285))*$B$5 -> 19409.995 | E286: =IF(-C286>D286,1,0) -> 0 | F286: =($B$13*_xlfn.STDEV.S($B36:$B285)-AVERAGE($B36:$B285))*$B$5 -> 25243.148 | G286: =IF(-C286>F286,1,0) -> 0 | H286: =($B$14*_xlfn.STDEV.S($B36:$B285)-AVERAGE($B36:$B285))*$B$5 -> 36185.172 | I286: =IF(-C286>H286,1,0) -> 0 | J286: =-_xlfn.PERCENTILE.INC($B36:$B285,1-0.9)*$B$5 -> 14332.289 | K286: =IF(-C286>J286,1,0) -> 0 | L286: =-_xlfn.PERCENTILE.INC($B36:$B285,1-0.95)*$B$5 -> 24460.565 | M286: =IF(-C286>L286,1,0) -> 0 | N286: =-_xlfn.PERCENTILE.INC($B36:$B285,1-0.99)*$B$5 -> 50685.129 | O286: =IF(-C286>N286,1,0) -> 0 | P286: =-(AVERAGE($B36:$B285)+_xlfn.STDEV.S($B36:$B285)*$C$12)*$B$5 -> 19927.263 | Q286: =IF(-C286>P286,1,0) -> 0 | R286: =-(AVERAGE($B36:$B285)+_xlfn.STDEV.S($B36:$B285)*$C$13)*$B$5 -> 25712.621 | S286: =IF(-C286>R286,1,0) -> 0 | T286: =-(AVERAGE($B36:$B285)+_xlfn.STDEV.S($B36:$B285)*$C$14)*$B$5 -> 36947.24 | U286: =IF(-C286>T286,1,0) -> 0 | V286: =-H286 -> -36185.172 | W286: =-N286 -> -50685.129 | X286: =-T286 -> -36947.24 | AN286: 0.77733758
A287: =Historical_Method!A281 -> 45972 | B287: =Historical_Method!E281 -> 0.0029028178 | C287: =B287*$B$5 -> 2902.8178 | D287: =($B$12*_xlfn.STDEV.S($B37:$B286)-AVERAGE($B37:$B286))*$B$5 -> 19403.908 | E287: =IF(-C287>D287,1,0) -> 0 | F287: =($B$13*_xlfn.STDEV.S($B37:$B286)-AVERAGE($B37:$B286))*$B$5 -> 25239.178 | G287: =IF(-C287>F287,1,0) -> 0 | H287: =($B$14*_xlfn.STDEV.S($B37:$B286)-AVERAGE($B37:$B286))*$B$5 -> 36185.174 | I287: =IF(-C287>H287,1,0) -> 0 | J287: =-_xlfn.PERCENTILE.INC($B37:$B286,1-0.9)*$B$5 -> 14332.289 | K287: =IF(-C287>J287,1,0) -> 0 | L287: =-_xlfn.PERCENTILE.INC($B37:$B286,1-0.95)*$B$5 -> 24460.565 | M287: =IF(-C287>L287,1,0) -> 0 | N287: =-_xlfn.PERCENTILE.INC($B37:$B286,1-0.99)*$B$5 -> 50685.129 | O287: =IF(-C287>N287,1,0) -> 0 | P287: =-(AVERAGE($B37:$B286)+_xlfn.STDEV.S($B37:$B286)*$C$12)*$B$5 -> 19921.364 | Q287: =IF(-C287>P287,1,0) -> 0 | R287: =-(AVERAGE($B37:$B286)+_xlfn.STDEV.S($B37:$B286)*$C$13)*$B$5 -> 25708.821 | S287: =IF(-C287>R287,1,0) -> 0 | T287: =-(AVERAGE($B37:$B286)+_xlfn.STDEV.S($B37:$B286)*$C$14)*$B$5 -> 36947.518 | U287: =IF(-C287>T287,1,0) -> 0 | V287: =-H287 -> -36185.174 | W287: =-N287 -> -50685.129 | X287: =-T287 -> -36947.518 | AN287: 0.43476607
A288: =Historical_Method!A282 -> 45973 | B288: =Historical_Method!E282 -> 0.014889166 | C288: =B288*$B$5 -> 14889.166 | D288: =($B$12*_xlfn.STDEV.S($B38:$B287)-AVERAGE($B38:$B287))*$B$5 -> 19414.608 | E288: =IF(-C288>D288,1,0) -> 0 | F288: =($B$13*_xlfn.STDEV.S($B38:$B287)-AVERAGE($B38:$B287))*$B$5 -> 25232.919 | G288: =IF(-C288>F288,1,0) -> 0 | H288: =($B$14*_xlfn.STDEV.S($B38:$B287)-AVERAGE($B38:$B287))*$B$5 -> 36147.102 | I288: =IF(-C288>H288,1,0) -> 0 | J288: =-_xlfn.PERCENTILE.INC($B38:$B287,1-0.9)*$B$5 -> 14332.289 | K288: =IF(-C288>J288,1,0) -> 0 | L288: =-_xlfn.PERCENTILE.INC($B38:$B287,1-0.95)*$B$5 -> 24460.565 | M288: =IF(-C288>L288,1,0) -> 0 | N288: =-_xlfn.PERCENTILE.INC($B38:$B287,1-0.99)*$B$5 -> 50685.129 | O288: =IF(-C288>N288,1,0) -> 0 | P288: =-(AVERAGE($B38:$B287)+_xlfn.STDEV.S($B38:$B287)*$C$12)*$B$5 -> 19930.56 | Q288: =IF(-C288>P288,1,0) -> 0 | R288: =-(AVERAGE($B38:$B287)+_xlfn.STDEV.S($B38:$B287)*$C$13)*$B$5 -> 25701.198 | S288: =IF(-C288>R288,1,0) -> 0 | T288: =-(AVERAGE($B38:$B287)+_xlfn.STDEV.S($B38:$B287)*$C$14)*$B$5 -> 36907.231 | U288: =IF(-C288>T288,1,0) -> 0 | V288: =-H288 -> -36147.102 | W288: =-N288 -> -50685.129 | X288: =-T288 -> -36907.231 | AN288: -0.37615607
A289: =Historical_Method!A283 -> 45974 | B289: =Historical_Method!E283 -> -0.027464618 | C289: =B289*$B$5 -> -27464.618 | D289: =($B$12*_xlfn.STDEV.S($B39:$B288)-AVERAGE($B39:$B288))*$B$5 -> 19363.775 | E289: =IF(-C289>D289,1,0) -> 1 | F289: =($B$13*_xlfn.STDEV.S($B39:$B288)-AVERAGE($B39:$B288))*$B$5 -> 25189.363 | G289: =IF(-C289>F289,1,0) -> 1 | H289: =($B$14*_xlfn.STDEV.S($B39:$B288)-AVERAGE($B39:$B288))*$B$5 -> 36117.195 | I289: =IF(-C289>H289,1,0) -> 0 | J289: =-_xlfn.PERCENTILE.INC($B39:$B288,1-0.9)*$B$5 -> 14332.289 | K289: =IF(-C289>J289,1,0) -> 1 | L289: =-_xlfn.PERCENTILE.INC($B39:$B288,1-0.95)*$B$5 -> 24460.565 | M289: =IF(-C289>L289,1,0) -> 1 | N289: =-_xlfn.PERCENTILE.INC($B39:$B288,1-0.99)*$B$5 -> 50685.129 | O289: =IF(-C289>N289,1,0) -> 0 | P289: =-(AVERAGE($B39:$B288)+_xlfn.STDEV.S($B39:$B288)*$C$12)*$B$5 -> 19880.373 | Q289: =IF(-C289>P289,1,0) -> 1 | R289: =-(AVERAGE($B39:$B288)+_xlfn.STDEV.S($B39:$B288)*$C$13)*$B$5 -> 25658.227 | S289: =IF(-C289>R289,1,0) -> 1 | T289: =-(AVERAGE($B39:$B288)+_xlfn.STDEV.S($B39:$B288)*$C$14)*$B$5 -> 36878.275 | U289: =IF(-C289>T289,1,0) -> 0 | V289: =-H289 -> -36117.195 | W289: =-N289 -> -50685.129 | X289: =-T289 -> -36878.275 | AN289: -0.13382296
A290: =Historical_Method!A284 -> 45975 | B290: =Historical_Method!E284 -> -0.011484067 | C290: =B290*$B$5 -> -11484.067 | D290: =($B$12*_xlfn.STDEV.S($B40:$B289)-AVERAGE($B40:$B289))*$B$5 -> 19617.266 | E290: =IF(-C290>D290,1,0) -> 0 | F290: =($B$13*_xlfn.STDEV.S($B40:$B289)-AVERAGE($B40:$B289))*$B$5 -> 25479.679 | G290: =IF(-C290>F290,1,0) -> 0 | H290: =($B$14*_xlfn.STDEV.S($B40:$B289)-AVERAGE($B40:$B289))*$B$5 -> 36476.591 | I290: =IF(-C290>H290,1,0) -> 0 | J290: =-_xlfn.PERCENTILE.INC($B40:$B289,1-0.9)*$B$5 -> 14518.866 | K290: =IF(-C290>J290,1,0) -> 0 | L290: =-_xlfn.PERCENTILE.INC($B40:$B289,1-0.95)*$B$5 -> 24937.292 | M290: =IF(-C290>L290,1,0) -> 0 | N290: =-_xlfn.PERCENTILE.INC($B40:$B289,1-0.99)*$B$5 -> 50685.129 | O290: =IF(-C290>N290,1,0) -> 0 | P290: =-(AVERAGE($B40:$B289)+_xlfn.STDEV.S($B40:$B289)*$C$12)*$B$5 -> 20137.129 | Q290: =IF(-C290>P290,1,0) -> 0 | R290: =-(AVERAGE($B40:$B289)+_xlfn.STDEV.S($B40:$B289)*$C$13)*$B$5 -> 25951.507 | S290: =IF(-C290>R290,1,0) -> 0 | T290: =-(AVERAGE($B40:$B289)+_xlfn.STDEV.S($B40:$B289)*$C$14)*$B$5 -> 37242.481 | U290: =IF(-C290>T290,1,0) -> 0 | V290: =-H290 -> -36476.591 | W290: =-N290 -> -50685.129 | X290: =-T290 -> -37242.481 | AN290: -1.3748958
A291: =Historical_Method!A285 -> 45978 | B291: =Historical_Method!E285 -> -0.01968789 | C291: =B291*$B$5 -> -19687.89 | D291: =($B$12*_xlfn.STDEV.S($B41:$B290)-AVERAGE($B41:$B290))*$B$5 -> 19689.609 | E291: =IF(-C291>D291,1,0) -> 0 | F291: =($B$13*_xlfn.STDEV.S($B41:$B290)-AVERAGE($B41:$B290))*$B$5 -> 25559.087 | G291: =IF(-C291>F291,1,0) -> 0 | H291: =($B$14*_xlfn.STDEV.S($B41:$B290)-AVERAGE($B41:$B290))*$B$5 -> 36569.252 | I291: =IF(-C291>H291,1,0) -> 0 | J291: =-_xlfn.PERCENTILE.INC($B41:$B290,1-0.9)*$B$5 -> 14518.866 | K291: =IF(-C291>J291,1,0) -> 1 | L291: =-_xlfn.PERCENTILE.INC($B41:$B290,1-0.95)*$B$5 -> 24937.292 | M291: =IF(-C291>L291,1,0) -> 0 | N291: =-_xlfn.PERCENTILE.INC($B41:$B290,1-0.99)*$B$5 -> 50685.129 | O291: =IF(-C291>N291,1,0) -> 0 | P291: =-(AVERAGE($B41:$B290)+_xlfn.STDEV.S($B41:$B290)*$C$12)*$B$5 -> 20210.099 | Q291: =IF(-C291>P291,1,0) -> 0 | R291: =-(AVERAGE($B41:$B290)+_xlfn.STDEV.S($B41:$B290)*$C$13)*$B$5 -> 26031.484 | S291: =IF(-C291>R291,1,0) -> 0 | T291: =-(AVERAGE($B41:$B290)+_xlfn.STDEV.S($B41:$B290)*$C$14)*$B$5 -> 37336.066 | U291: =IF(-C291>T291,1,0) -> 0 | V291: =-H291 -> -36569.252 | W291: =-N291 -> -50685.129 | X291: =-T291 -> -37336.066 | AN291: -0.23817374
A292: =Historical_Method!A286 -> 45979 | B292: =Historical_Method!E286 -> 0.0007651285 | C292: =B292*$B$5 -> 765.1285 | D292: =($B$12*_xlfn.STDEV.S($B42:$B291)-AVERAGE($B42:$B291))*$B$5 -> 19864.673 | E292: =IF(-C292>D292,1,0) -> 0 | F292: =($B$13*_xlfn.STDEV.S($B42:$B291)-AVERAGE($B42:$B291))*$B$5 -> 25744.426 | G292: =IF(-C292>F292,1,0) -> 0 | H292: =($B$14*_xlfn.STDEV.S($B42:$B291)-AVERAGE($B42:$B291))*$B$5 -> 36773.865 | I292: =IF(-C292>H292,1,0) -> 0 | J292: =-_xlfn.PERCENTILE.INC($B42:$B291,1-0.9)*$B$5 -> 14633.173 | K292: =IF(-C292>J292,1,0) -> 0 | L292: =-_xlfn.PERCENTILE.INC($B42:$B291,1-0.95)*$B$5 -> 24937.292 | M292: =IF(-C292>L292,1,0) -> 0 | N292: =-_xlfn.PERCENTILE.INC($B42:$B291,1-0.99)*$B$5 -> 50685.129 | O292: =IF(-C292>N292,1,0) -> 0 | P292: =-(AVERAGE($B42:$B291)+_xlfn.STDEV.S($B42:$B291)*$C$12)*$B$5 -> 20386.073 | Q292: =IF(-C292>P292,1,0) -> 0 | R292: =-(AVERAGE($B42:$B291)+_xlfn.STDEV.S($B42:$B291)*$C$13)*$B$5 -> 26217.65 | S292: =IF(-C292>R292,1,0) -> 0 | T292: =-(AVERAGE($B42:$B291)+_xlfn.STDEV.S($B42:$B291)*$C$14)*$B$5 -> 37542.021 | U292: =IF(-C292>T292,1,0) -> 0 | V292: =-H292 -> -36773.865 | W292: =-N292 -> -50685.129 | X292: =-T292 -> -37542.021 | AN292: -0.26638749
... A530: =Historical_Method!A524 -> 46325 | B530: =Historical_Method!E524 -> -0.021741415 | C530: =B530*$B$5 -> -21741.415 | D530: =($B$12*_xlfn.STDEV.S($B280:$B529)-AVERAGE($B280:$B529))*$B$5 -> 16693.21 | E530: =IF(-C530>D530,1,0) -> 1 | F530: =($B$13*_xlfn.STDEV.S($B280:$B529)-AVERAGE($B280:$B529))*$B$5 -> 21560.862 | G530: =IF(-C530>F530,1,0) -> 1 | H530: =($B$14*_xlfn.STDEV.S($B280:$B529)-AVERAGE($B280:$B529))*$B$5 -> 30691.769 | I530: =IF(-C530>H530,1,0) -> 0 | J530: =-_xlfn.PERCENTILE.INC($B280:$B529,1-0.9)*$B$5 -> 18170.277 | K530: =IF(-C530>J530,1,0) -> 1 | L530: =-_xlfn.PERCENTILE.INC($B280:$B529,1-0.95)*$B$5 -> 22533.36 | M530: =IF(-C530>L530,1,0) -> 0 | N530: =-_xlfn.PERCENTILE.INC($B280:$B529,1-0.99)*$B$5 -> 34153.907 | O530: =IF(-C530>N530,1,0) -> 0 | P530: =-(AVERAGE($B280:$B529)+_xlfn.STDEV.S($B280:$B529)*$C$12)*$B$5 -> 17124.86 | Q530: =IF(-C530>P530,1,0) -> 1 | R530: =-(AVERAGE($B280:$B529)+_xlfn.STDEV.S($B280:$B529)*$C$13)*$B$5 -> 21952.629 | S530: =IF(-C530>R530,1,0) -> 0 | T530: =-(AVERAGE($B280:$B529)+_xlfn.STDEV.S($B280:$B529)*$C$14)*$B$5 -> 31327.7 | U530: =IF(-C530>T530,1,0) -> 0 | V530: =-H530 -> -30691.769 | W530: =-N530 -> -34153.907 | X530: =-T530 -> -31327.7 | AN530: -1.4950608
AN531: 1.3638622
AN532: 0.89518498
AN533: -0.71948023
AN534: -1.5025035
AN535: -2.9645288
AN536: -0.54349551
AN537: 2.420415
AN538: 0.43488427
AN539: -0.55957229
AN540: 0.46508021
AN541: -1.5609584
AN542: -0.29732336
... AN10030: -0.1828499
